{
  "parameters": {
    "autoHideDuration": {
      "type": { "name": "number | null", "description": "number | null" },
      "default": "null"
    },
    "disableWindowBlurListener": {
      "type": { "name": "boolean", "description": "boolean" },
      "default": "false"
    },
    "onClose": {
      "type": {
        "name": "(event: React.SyntheticEvent&lt;any&gt | Event | null, reason: SnackbarCloseReason) =&gt void",
        "description": "(event: React.SyntheticEvent&lt;any&gt | Event | null, reason: SnackbarCloseReason) =&gt void"
      }
    },
    "open": { "type": { "name": "boolean", "description": "boolean" } },
    "ref": { "type": { "name": "React.Ref&lt;any&gt", "description": "React.Ref&lt;any&gt" } },
    "resumeHideDuration": { "type": { "name": "number", "description": "number" } }
  },
  "returnValue": {
    "getRootProps": {
      "type": {
        "name": "<TOther extends Record<string, ((event: any) => void) | undefined> = {}>(externalProps?: TOther) => UseSnackbarRootSlotProps<TOther>",
        "description": "Resolver for the root slot's props."
      },
      "required": true
    },
    "onClickAway": {
      "type": {
        "name": "(event: React.SyntheticEvent<any> | Event) => void",
        "description": "Callback fired when a \"click away\" event is detected."
      },
      "required": true
    }
  },
  "name": "useSnackbar",
  "filename": "/packages/mui-base/src/useSnackbar/useSnackbar.ts",
  "demos": "<ul><li><a href=\"/base/react-snackbar/#hook\">Unstyled Snackbar</a></li></ul>"
}
