{
  "name": "Button",
  "filename": "/packages/material-ui/src/Button/Button.js",
  "description": "",
  "props": {
    "children": { "type": { "name": "node" }, "required": false },
    "classes": { "type": { "name": "object" }, "required": false },
    "className": { "type": { "name": "string" }, "required": false, "description": "@ignore" },
    "color": {
      "type": {
        "name": "enum",
        "description": "'inherit'<br>&#124;&nbsp;'primary'<br>&#124;&nbsp;'secondary'"
      },
      "required": false,
      "default": "'primary'"
    },
    "component": { "type": { "name": "elementType" }, "required": false },
    "disabled": { "type": { "name": "bool" }, "required": false, "default": "false" },
    "disableElevation": { "type": { "name": "bool" }, "required": false, "default": "false" },
    "disableFocusRipple": { "type": { "name": "bool" }, "required": false, "default": "false" },
    "disableRipple": { "type": { "name": "bool" }, "required": false },
    "endIcon": { "type": { "name": "node" }, "required": false },
    "focusVisibleClassName": {
      "type": { "name": "string" },
      "required": false,
      "description": "@ignore"
    },
    "fullWidth": { "type": { "name": "bool" }, "required": false, "default": "false" },
    "href": { "type": { "name": "string" }, "required": false },
    "size": {
      "type": {
        "name": "enum",
        "description": "'large'<br>&#124;&nbsp;'medium'<br>&#124;&nbsp;'small'"
      },
      "required": false,
      "default": "'medium'"
    },
    "startIcon": { "type": { "name": "node" }, "required": false },
    "type": {
      "type": {
        "name": "union",
        "value": [
          {
            "name": "enum",
            "value": [
              { "value": "'button'", "computed": false },
              { "value": "'reset'", "computed": false },
              { "value": "'submit'", "computed": false }
            ]
          },
          { "name": "string" }
        ]
      },
      "required": false,
      "description": "@ignore"
    },
    "variant": {
      "type": {
        "name": "union",
        "description": "'contained'<br>&#124;&nbsp;'outlined'<br>&#124;&nbsp;'text'<br>&#124;&nbsp;string"
      },
      "required": false,
      "default": "'text'"
    }
  },
  "spread": true,
  "styles": {
    "name": "MuiButton",
    "globalClasses": {
      "root": "MuiButton-root",
      "label": "MuiButton-label",
      "text": "MuiButton-text",
      "textPrimary": "MuiButton-textPrimary",
      "textSecondary": "MuiButton-textSecondary",
      "outlined": "MuiButton-outlined",
      "outlinedPrimary": "MuiButton-outlinedPrimary",
      "outlinedSecondary": "MuiButton-outlinedSecondary",
      "contained": "MuiButton-contained",
      "containedPrimary": "MuiButton-containedPrimary",
      "containedSecondary": "MuiButton-containedSecondary",
      "disableElevation": "MuiButton-disableElevation",
      "focusVisible": "Mui-focusVisible",
      "disabled": "Mui-disabled",
      "colorInherit": "MuiButton-colorInherit",
      "textSizeSmall": "MuiButton-textSizeSmall",
      "textSizeLarge": "MuiButton-textSizeLarge",
      "outlinedSizeSmall": "MuiButton-outlinedSizeSmall",
      "outlinedSizeLarge": "MuiButton-outlinedSizeLarge",
      "containedSizeSmall": "MuiButton-containedSizeSmall",
      "containedSizeLarge": "MuiButton-containedSizeLarge",
      "sizeSmall": "MuiButton-sizeSmall",
      "sizeLarge": "MuiButton-sizeLarge",
      "fullWidth": "MuiButton-fullWidth",
      "startIcon": "MuiButton-startIcon",
      "endIcon": "MuiButton-endIcon",
      "iconSizeSmall": "MuiButton-iconSizeSmall",
      "iconSizeMedium": "MuiButton-iconSizeMedium",
      "iconSizeLarge": "MuiButton-iconSizeLarge"
    }
  },
  "forwardsRefTo": "HTMLButtonElement",
  "inheritance": { "component": "ButtonBase", "pathname": "/api/button-base/" },
  "demos": "- [Button Group](/components/button-group/)\n- [Buttons](/components/buttons/)"
}
