{
  "props": {
    "open": { "type": { "name": "bool" }, "required": true },
    "children": { "type": { "name": "custom", "description": "element" } },
    "disableAutoFocus": { "type": { "name": "bool" } },
    "disableEnforceFocus": { "type": { "name": "bool" } },
    "disableRestoreFocus": { "type": { "name": "bool" } },
    "getTabbable": { "type": { "name": "func" } },
    "isEnabled": {
      "type": { "name": "func" },
      "default": "function defaultIsEnabled() {\n  return true;\n}"
    }
  },
  "name": "Unstable_TrapFocus",
  "styles": { "classes": [], "globalClasses": {}, "name": null },
  "spread": false,
  "filename": "/packages/material-ui-unstyled/src/Unstable_TrapFocus/Unstable_TrapFocus.js",
  "inheritance": null,
  "demos": "<ul><li><a href=\"/components/trap-focus/\">Trap Focus</a></li></ul>",
  "styledComponent": true,
  "cssComponent": false
}
