{
  "build/umd/material-ui.development.js": {
    "bundled": 986735,
    "minified": 361055,
    "gzipped": 94085
  },
  "build/umd/material-ui.production.min.js": {
    "bundled": 815902,
    "minified": 319781,
    "gzipped": 84808
  },
  "build/dist/material-ui.esm.js": {
    "bundled": 583544,
    "minified": 284185,
    "gzipped": 63320,
    "treeshaked": {
      "rollup": {
        "code": 196284,
        "import_statements": 1939
      },
      "webpack": {
        "code": 203380
      }
    }
  }
}
