{
  "build/dist/material-ui-pickers.esm.js": {
    "bundled": 105850,
    "minified": 61611,
    "gzipped": 14494,
    "treeshaked": {
      "rollup": {
        "code": 48239,
        "import_statements": 1323
      },
      "webpack": {
        "code": 55233
      }
    }
  },
  "build/dist/material-ui-pickers.umd.js": {
    "bundled": 219608,
    "minified": 94966,
    "gzipped": 25370
  },
  "build/dist/material-ui-pickers.umd.min.js": {
    "bundled": 199836,
    "minified": 89281,
    "gzipped": 24151
  }
}
